eight-bit-alu/rtl/ula_74181.sv
module ula_74181
(
    input logic [3:0] a, b, s,
    input logic m, c_in,

    output logic [3:0] f,
    output logic a_eq_b, c_out
);

logic [4:0] full_calc;

always @(*)
    begin
        if (m)
            begin
                case (s)
                    4'b0000: f = ~a;
                    4'b0001: f = ~(a | b);
                    4'b0010: f = ~a & b;
                    4'b0011: f = 4'b0000;
                    4'b0100: f = ~a & ~b;
                    4'b0101: f = ~b;
                    4'b0110: f = a ^ b;
                    4'b0111: f = a & ~b;
                    4'b1000: f = ~a | b;
                    4'b1001: f = ~(a ^ b);
                    4'b1010: f = b;
                    4'b1011: f = a & b;
                    4'b1100: f = 4'b1111;
                    4'b1101: f = a | ~b;
                    4'b1110: f = a | b;
                    4'b1111: f = a;
                    default: f = 4'b0000;
                endcase
                
                full_calc = f;
                c_out = full_calc[4];
            end
        else if (c_in)
            begin
                case (s)
                    4'b0000: full_calc = a;
                    4'b0001: full_calc = a | b;
                    4'b0010: full_calc = a | ~b;
                    4'b0011: full_calc = 5'b11111;
                    4'b0100: full_calc = a + a & ~b;
                    4'b0101: full_calc = (a | b) + (a & ~b);
                    4'b0110: full_calc = a - b - 1;
                    4'b0111: full_calc = (a & (~b)) - 1;
                    4'b1000: full_calc = a + (a & b);
                    4'b1001: full_calc = a + b;
                    4'b1010: full_calc = a | ~b + (a & b);
                    4'b1011: full_calc = (a & b) - 1;
                    4'b1100: full_calc = a + a;
                    4'b1101: full_calc = (a | b) + a;
                    4'b1110: full_calc = (a | ~b) + a;
                    4'b1111: full_calc = a - 1;
                    default: full_calc = 5'b00000;
                endcase

                f = full_calc[3:0];
                c_out = full_calc[4];
            end
        else
            begin
                case (s)
                    4'b0000: full_calc = a + 1;
                    4'b0001: full_calc = (a | b) + 1;
                    4'b0010: full_calc = (a | ~b) + 1;
                    4'b0011: full_calc = 5'b00000;
                    4'b0100: full_calc = (a + (a & ~b)) + 1;
                    4'b0101: full_calc = ((a | b) + (a & ~b)) + 1;
                    4'b0110: full_calc = (a - b);
                    4'b0111: full_calc = (a & ~b);
                    4'b1000: full_calc = (a + (a & b)) + 1;
                    4'b1001: full_calc = (a + b) + 1;
                    4'b1010: full_calc = ((a | ~b) + (a & b)) + 1;
                    4'b1011: full_calc = (a & b);
                    4'b1100: full_calc = (a + a) + 1;
                    4'b1101: full_calc = ((a | b) + a) + 1;
                    4'b1110: full_calc = ((a | ~b) + a) + 1;
                    4'b1111: full_calc = a;
                    default: full_calc = 5'b00000;
                endcase

                f = full_calc[3:0];
                c_out = full_calc[4];
            end

        a_eq_b = (a == b) ? 1'b1 : 1'b0;
    end
endmodule

eight-bit-alu/tb/tb_ula_74181.sv
module tb_ula_74181;

logic [3:0] a, b, s;
logic m, c_in;

logic [3:0] f;
logic a_eq_b, c_out;

ula_74181 dut
(
    .a(a),
    .b(b),
    .s(s),
    .m(m),
    .c_in(c_in),
    .f(f),
    .a_eq_b(a_eq_b),
    .c_out(c_out)
);

initial
    begin
        $dumpfile("ula_74181.vcd");
        $dumpvars(0, tb_ula_74181);

        $display("Inicio da simulacao");

        for (int mode = 1'b0; mode <= 1'b1; mode++)
            begin
                m = mode;

                for (int cin = 1'b0; cin <= 1'b1; cin++)
                    begin
                        c_in = cin;

                        for (int selection = 4'b0000; selection <= 4'b1111; selection++)
                            begin
                                s = selection;
                                
                                a = 4'b0100;
                                b = 4'b0011;

                                #10;

                                $display("M: %b, S: %0d, A: %0d, B: %0d, C_IN: %b, F: %0d, C_OUT: %b", m, s, a, b, c_in, f, c_out);
                            end
                    end
            end

        $display("Fim da simulacao");

        $finish;
    end
endmodule

eight-bit-alu/ula_74181.vcd
$date
	Sun Aug 10 23:15:50 2025
$end
$version
	Icarus Verilog
$end
$timescale
	1s
$end
$scope module tb_ula_74181 $end
$var wire 4 ! f [3:0] $end
$var wire 1 " c_out $end
$var wire 1 # a_eq_b $end
$var reg 4 $ a [3:0] $end
$var reg 4 % b [3:0] $end
$var reg 1 & c_in $end
$var reg 1 ' m $end
$var reg 4 ( s [3:0] $end
$scope module dut $end
$var wire 4 ) a [3:0] $end
$var wire 4 * b [3:0] $end
$var wire 1 & c_in $end
$var wire 1 ' m $end
$var wire 4 + s [3:0] $end
$var reg 1 # a_eq_b $end
$var reg 1 " c_out $end
$var reg 4 , f [3:0] $end
$var reg 5 - full_calc [4:0] $end
$upscope $end
$scope begin $ivl_for_loop0 $end
$var integer 32 . mode [31:0] $end
$scope begin $ivl_for_loop1 $end
$var integer 32 / cin [31:0] $end
$scope begin $ivl_for_loop2 $end
$var integer 32 0 selection [31:0] $end
$upscope $end
$upscope $end
$upscope $end
$upscope $end
$enddefinitions $end
$comment Show the parameter values. $end
$dumpall
$end
#0
$dumpvars
b0 0
b0 /
b0 .
b101 -
b101 ,
b0 +
b11 *
b100 )
b0 (
0'
0&
b11 %
b100 $
0#
0"
b101 !
$end
#10
b1000 !
b1000 ,
b1000 -
b1 (
b1 +
b1 0
#20
1"
b1101 !
b1101 ,
b11101 -
b10 (
b10 +
b10 0
#30
0"
b0 !
b0 ,
b0 -
b11 (
b11 +
b11 0
#40
b1001 !
b1001 ,
b1001 -
b100 (
b100 +
b100 0
#50
b1100 !
b1100 ,
b1100 -
b101 (
b101 +
b101 0
#60
b1 !
b1 ,
b1 -
b110 (
b110 +
b110 0
#70
b100 !
b100 ,
b100 -
b111 (
b111 +
b111 0
#80
b101 !
b101 ,
b101 -
b1000 (
b1000 +
b1000 0
#90
b1000 !
b1000 ,
b1000 -
b1001 (
b1001 +
b1001 0
#100
1"
b1101 !
b1101 ,
b11101 -
b1010 (
b1010 +
b1010 0
#110
0"
b0 !
b0 ,
b0 -
b1011 (
b1011 +
b1011 0
#120
b1001 !
b1001 ,
b1001 -
b1100 (
b1100 +
b1100 0
#130
b1100 !
b1100 ,
b1100 -
b1101 (
b1101 +
b1101 0
#140
b1 !
b1 ,
b1 -
b1110 (
b1110 +
b1110 0
#150
b100 !
b100 ,
b100 -
b1111 (
b1111 +
b1111 0
#160
b0 (
b0 +
1&
b1 /
b0 0
#170
b111 !
b111 ,
b111 -
b1 (
b1 +
b1 0
#180
1"
b1100 !
b1100 ,
b11100 -
b10 (
b10 +
b10 0
#190
b1111 !
b1111 ,
b11111 -
b11 (
b11 +
b11 0
#200
0"
b1000 !
b1000 ,
b1000 -
b100 (
b100 +
b100 0
#210
b1011 !
b1011 ,
b1011 -
b101 (
b101 +
b101 0
#220
b0 !
b0 ,
b0 -
b110 (
b110 +
b110 0
#230
b11 !
b11 ,
b11 -
b111 (
b111 +
b111 0
#240
b100 !
b100 ,
b100 -
b1000 (
b1000 +
b1000 0
#250
b111 !
b111 ,
b111 -
b1001 (
b1001 +
b1001 0
#260
1"
b1100 !
b1100 ,
b11100 -
b1010 (
b1010 +
b1010 0
#270
b1111 !
b1111 ,
b11111 -
b1011 (
b1011 +
b1011 0
#280
0"
b1000 !
b1000 ,
b1000 -
b1100 (
b1100 +
b1100 0
#290
b1011 !
b1011 ,
b1011 -
b1101 (
b1101 +
b1101 0
#300
b0 !
b0 ,
b0 -
b1110 (
b1110 +
b1110 0
#310
b11 !
b11 ,
b11 -
b1111 (
b1111 +
b1111 0
#320
b1011 -
b1011 !
b1011 ,
b0 (
b0 +
0&
1'
b1 .
b0 /
b0 0
#330
b1000 -
b1000 !
b1000 ,
b1 (
b1 +
b1 0
#340
b11 -
b11 !
b11 ,
b10 (
b10 +
b10 0
#350
b0 -
b0 !
b0 ,
b11 (
b11 +
b11 0
#360
b1000 -
b1000 !
b1000 ,
b100 (
b100 +
b100 0
#370
b1100 -
b1100 !
b1100 ,
b101 (
b101 +
b101 0
#380
b111 -
b111 !
b111 ,
b110 (
b110 +
b110 0
#390
b100 -
b100 !
b100 ,
b111 (
b111 +
b111 0
#400
b1011 -
b1011 !
b1011 ,
b1000 (
b1000 +
b1000 0
#410
b1000 -
b1000 !
b1000 ,
b1001 (
b1001 +
b1001 0
#420
b11 -
b11 !
b11 ,
b1010 (
b1010 +
b1010 0
#430
b0 -
b0 !
b0 ,
b1011 (
b1011 +
b1011 0
#440
b1111 -
b1111 !
b1111 ,
b1100 (
b1100 +
b1100 0
#450
b1100 -
b1100 !
b1100 ,
b1101 (
b1101 +
b1101 0
#460
b111 -
b111 !
b111 ,
b1110 (
b1110 +
b1110 0
#470
b100 -
b100 !
b100 ,
b1111 (
b1111 +
b1111 0
#480
b1011 -
b1011 !
b1011 ,
b0 (
b0 +
1&
b1 /
b0 0
#490
b1000 -
b1000 !
b1000 ,
b1 (
b1 +
b1 0
#500
b11 -
b11 !
b11 ,
b10 (
b10 +
b10 0
#510
b0 -
b0 !
b0 ,
b11 (
b11 +
b11 0
#520
b1000 -
b1000 !
b1000 ,
b100 (
b100 +
b100 0
#530
b1100 -
b1100 !
b1100 ,
b101 (
b101 +
b101 0
#540
b111 -
b111 !
b111 ,
b110 (
b110 +
b110 0
#550
b100 -
b100 !
b100 ,
b111 (
b111 +
b111 0
#560
b1011 -
b1011 !
b1011 ,
b1000 (
b1000 +
b1000 0
#570
b1000 -
b1000 !
b1000 ,
b1001 (
b1001 +
b1001 0
#580
b11 -
b11 !
b11 ,
b1010 (
b1010 +
b1010 0
#590
b0 -
b0 !
b0 ,
b1011 (
b1011 +
b1011 0
#600
b1111 -
b1111 !
b1111 ,
b1100 (
b1100 +
b1100 0
#610
b1100 -
b1100 !
b1100 ,
b1101 (
b1101 +
b1101 0
#620
b111 -
b111 !
b111 ,
b1110 (
b1110 +
b1110 0
#630
b100 -
b100 !
b100 ,
b1111 (
b1111 +
b1111 0
#640
b10 .
b10 /
b10000 0
